corpus2alpino/__init__.py
corpus2alpino/__main__.py
corpus2alpino/abstracts.py
corpus2alpino/converter.py
corpus2alpino/models.py
corpus2alpino/annotators/__init__.py
corpus2alpino/annotators/alpino.py
corpus2alpino/annotators/alpino_client.py
corpus2alpino/annotators/enrich_lassy.py
corpus2alpino/collectors/__init__.py
corpus2alpino/collectors/filesystem.py
corpus2alpino/readers/__init__.py
corpus2alpino/readers/alpino_brackets.py
corpus2alpino/readers/auto.py
corpus2alpino/readers/chat.py
corpus2alpino/readers/folia.py
corpus2alpino/readers/lassy.py
corpus2alpino/readers/paqu.py
corpus2alpino/readers/tei.py
corpus2alpino/readers/tokenizer.py
corpus2alpino/targets/__init__.py
corpus2alpino/targets/console.py
corpus2alpino/targets/filesystem.py
corpus2alpino/targets/memory.py
corpus2alpino/writers/__init__.py
corpus2alpino/writers/lassy.py
corpus2alpino/writers/paqu.py
tests/__init__.py
tests/test_corpus2alpino.py
tests/test_enrich_lassy.py
tests/update_test_outputs.py
corpus2alpino-0.3.13.dist-info/LICENSE
corpus2alpino-0.3.13.dist-info/METADATA
corpus2alpino-0.3.13.dist-info/WHEEL
corpus2alpino-0.3.13.dist-info/entry_points.txt
corpus2alpino-0.3.13.dist-info/top_level.txt
corpus2alpino-0.3.13.dist-info/zip-safe
corpus2alpino-0.3.13.dist-info/RECORD
