Metadata-Version: 2.1
Name: corpus2alpino
Version: 0.3.13
Summary: Converts FoLiA and TEI files to Alpino XML files
Home-page: https://github.com/UUDigitalHumanitieslab/corpus2alpino
Author: Sheean Spoel, Digital Humanities Lab, Utrecht University
Author-email: s.j.j.spoel@uu.nl
License: MIT
Classifier: Programming Language :: Python :: 3
Classifier: License :: OSI Approved :: MIT License
Classifier: Operating System :: OS Independent
Requires-Python: >=3.8
License-File: LICENSE
Requires-Dist: argparse
Requires-Dist: chamd >=0.5.8
Requires-Dist: folia
Requires-Dist: spacy
Requires-Dist: tei-reader
Requires-Dist: tqdm
